ts3ekkomanage/__init__.py
ts3ekkomanage/entrypoint.py
ts3ekkomanage/manager.py
ts3ekkomanage/model.py
ts3ekkomanage/webhooks.py
ts3ekkomanage-0.0.4.dist-info/DESCRIPTION.rst
ts3ekkomanage-0.0.4.dist-info/METADATA
ts3ekkomanage-0.0.4.dist-info/RECORD
ts3ekkomanage-0.0.4.dist-info/WHEEL
ts3ekkomanage-0.0.4.dist-info/entry_points.txt
ts3ekkomanage-0.0.4.dist-info/metadata.json
ts3ekkomanage-0.0.4.dist-info/top_level.txt
