Metadata-Version: 2.0
Name: ts3ekkomanage
Version: 0.0.4
Summary: ts3ekkomanage
Home-page: https://gitlab.com/networkjanitor/ts3ekkomanage
Author: Xyoz Netsphere
Author-email: nanoowl@xyooz.net
License: MIT
Platform: UNKNOWN
Classifier: Development Status :: 3 - Alpha
Classifier: License :: OSI Approved :: MIT License
Classifier: Programming Language :: Python :: 3
Classifier: Programming Language :: Python :: 3.6
Requires-Dist: SQLAlchemy
Requires-Dist: SQLAlchemy-utils
Requires-Dist: psycopg2
Requires-Dist: bottle
Requires-Dist: sqlalchemy-seed
Requires-Dist: docker
Requires-Dist: ts3ekkoutil (>=0.0.19)
Requires-Dist: PyYAML
Requires-Dist: sphinx
Requires-Dist: sphinx-autobuild
Requires-Dist: sphinx-rtd-theme
Requires-Dist: ts3ekkoclient (==0.0.10)
